celery_sqlcommenter/__init__.py
celery_sqlcommenter/base_task.py
celery_sqlcommenter/query_wrapper.py
celery_sqlcommenter/utils.py
celery_sqlcommenter-0.2.dist-info/METADATA
celery_sqlcommenter-0.2.dist-info/WHEEL
celery_sqlcommenter-0.2.dist-info/RECORD
