Metadata-Version: 2.3
Name: celery-sqlcommenter
Version: 0.2
Summary: instrument sql queries running on celery
License: MIT
Author: Yash Kumar Verma
Author-email: yk.verma2000@gmail.com
Requires-Python: >=3.8,<=3.14
Classifier: License :: OSI Approved :: MIT License
Classifier: Programming Language :: Python :: 3
Classifier: Programming Language :: Python :: 3.8
Classifier: Programming Language :: Python :: 3.9
Classifier: Programming Language :: Python :: 3.10
Classifier: Programming Language :: Python :: 3.11
Classifier: Programming Language :: Python :: 3.12
Classifier: Programming Language :: Python :: 3.13
Requires-Dist: celery (>=5.2.0,<6.0.0)
Requires-Dist: django (>=2.2,<5.0)
Requires-Dist: django-prometheus (>=2.4.1,<3.0.0)
